{"version":1,"resource":"file:///home/hellsing/Development/react-admin-dashboard/src/scenes/global/Sidebar.jsx","entries":[{"id":"pnQo.jsx","source":"undoRedo.source","timestamp":1679240391885},{"id":"Zscj.jsx","timestamp":1679240527448},{"id":"t8cm.jsx","timestamp":1679240563544},{"id":"Pa2c.jsx","timestamp":1679241214241},{"id":"ekrP.jsx","timestamp":1679241435605},{"id":"lVA4.jsx","timestamp":1679241822074},{"id":"s0uU.jsx","timestamp":1679241862224},{"id":"4rW9.jsx","timestamp":1679241907003},{"id":"pGj4.jsx","timestamp":1679255743617},{"id":"mUIl.jsx","timestamp":1679255792693},{"id":"pcUv.jsx","timestamp":1679256069593},{"id":"u3mq.jsx","timestamp":1679256092640},{"id":"iKLs.jsx","timestamp":1679256120696},{"id":"Akif.jsx","timestamp":1679272602451},{"id":"CUNL.jsx","timestamp":1679277769327}]}